omnipack/__init__.py
omnipack/version.py
omnipack/command/__init__.py
omnipack/command/aliased_group.py
omnipack/command/cli.py
omnipack/command/fileio.py
omnipack/command/os.py
omnipack/fileio/__init__.py
omnipack/fileio/file_conversion.py
omnipack/fileio/file_to_config.py
omnipack/fileio/file_utils.py
omnipack/image/__init__.py
omnipack/image/image_annotator.py
omnipack/image/image_augmentor.py
omnipack/image/transformer.py
omnipack/os/__init__.py
omnipack/os/network.py
omnipack/os/process.py
omnipack/os/sys_info.py
omnipack/utils/__init__.py
omnipack/utils/profiler.py
omnipack/utils/time.py
omnipack-0.0.2.dist-info/LICENSE
omnipack-0.0.2.dist-info/METADATA
omnipack-0.0.2.dist-info/WHEEL
omnipack-0.0.2.dist-info/entry_points.txt
omnipack-0.0.2.dist-info/top_level.txt
omnipack-0.0.2.dist-info/RECORD
