Metadata-Version: 2.1
Name: omnipack
Version: 0.0.2
Summary: A robust collection of useful scripts
Home-page: https://github.com/FrankLeeeee/powerpack
Author: Li Shenggui
Author-email: somerlee.9@gmail.com
License: Apache License 2.0
Keywords: Python,scripts
Platform: UNKNOWN
Classifier: Development Status :: 4 - Beta
Classifier: License :: OSI Approved :: Apache Software License
Classifier: Operating System :: OS Independent
Classifier: Programming Language :: Python :: 3
Classifier: Programming Language :: Python :: 3.5
Classifier: Programming Language :: Python :: 3.6
Classifier: Programming Language :: Python :: 3.7
Requires-Dist: click (<7.0)
Requires-Dist: pillow
Requires-Dist: pandas
Requires-Dist: pyyaml
Requires-Dist: psutil
